attach/__init__.py
attach/attach.py
attach-0.1.dist-info/METADATA
attach-0.1.dist-info/RECORD
attach-0.1.dist-info/WHEEL
attach-0.1.dist-info/top_level.txt
