Metadata-Version: 2.1
Name: attach
Version: 0.1
Summary: Attaching and detaching namespaces to keep globals clean
Home-page: https://github.com/yatharth/attach
Author: Yatharth Agarwal
Author-email: yatharth999@gmail.com
License: UNKNOWN
Platform: UNKNOWN
Classifier: Programming Language :: Python :: 3.5
Classifier: License :: OSI Approved :: MIT License
Classifier: Operating System :: OS Independent
Classifier: Development Status :: 4 - Beta
